ufo_mssm/__init__.py
ufo_mssm/build_restrict.py
ufo_mssm/coupling_orders.py
ufo_mssm/couplings.py
ufo_mssm/decays.py
ufo_mssm/function_library.py
ufo_mssm/lorentz.py
ufo_mssm/object_library.py
ufo_mssm/parameters.py
ufo_mssm/particles.py
ufo_mssm/restrict_default.dat
ufo_mssm/restrict_no_b_mass.dat
ufo_mssm/restrict_no_masses.dat
ufo_mssm/restrict_no_tau_mass.dat
ufo_mssm/vertices.py
ufo_mssm/write_param_card.py
ufo_mssm-1.0.0.dist-info/WHEEL
ufo_mssm-1.0.0.dist-info/METADATA
ufo_mssm-1.0.0.dist-info/RECORD
